LICENSE.txt
README.md
setup.cfg
setup.py
conlp/__init__.py
conlp/download.py
conlp/keyword.py
conlp/preprocess.py
conlp/sentiment.py
conlp.egg-info/PKG-INFO
conlp.egg-info/SOURCES.txt
conlp.egg-info/dependency_links.txt
conlp.egg-info/requires.txt
conlp.egg-info/top_level.txt