Metadata-Version: 2.1
Name: conlp
Version: 0.0.7
Summary: TYPE YOUR DESCRIPTION HERE
Home-page: https://github.com/SOCIALSCIENCEai/coNLP
Download-URL: https://github.com/SOCIALSCIENCEai/coNLP/archive/refs/tags/0.0.7.tar.gz
Author: Nick S.H Oh
Author-email: nick.sh.oh@socialscience.ai
License: Apache-2.0
Keywords: NLP,SOCIAL SCIENCE
Platform: UNKNOWN
License-File: LICENSE.txt
